medhaAI/__init__.py
medhaAI/config.py
medhaAI/exceptions.py
medhaAI/logging_utils.py
medhaAI/multi_agent_system.py
medhaAI/agents/__init__.py
medhaAI/agents/base.py
medhaAI/agents/specialized_agents.py
medhaAI/execution/__init__.py
medhaAI/execution/base.py
medhaAI/execution/parallel.py
medhaAI/llm/__init__.py
medhaAI/llm/base.py
medhaAI/llm/openai_llm.py
medhaAI/memory/__init__.py
medhaAI/memory/base.py
medhaAI/memory/in_memory.py
medhaAI/planning/__init__.py
medhaAI/planning/base.py
medhaAI/planning/hierarchical.py
medhaAI/stream/__init__.py
medhaAI/stream/live_stream.py
medhaAI/tools/__init__.py
medhaAI/tools/base.py
medhaAI/tools/web_scraper.py
medhaAI/utils/__init__.py
medhaAI/utils/live_stream.py
medhaAI/utils/performance_monitoring.py
medhaAI/utils/tracing.py
medhaai-0.4.0.dist-info/LICENSE
medhaai-0.4.0.dist-info/METADATA
medhaai-0.4.0.dist-info/WHEEL
medhaai-0.4.0.dist-info/top_level.txt
medhaai-0.4.0.dist-info/RECORD
