Metadata-Version: 2.1
Name: medhaai
Version: 0.4.0
Summary: A flexible and powerful multi-agent AI framework for building advanced AI applications
Home-page: https://github.com/sarath59/medhaAI
Author: Sarath Kavuru
Author-email: sarathc225@gmail.com
Classifier: Development Status :: 3 - Alpha
Classifier: Intended Audience :: Developers
Classifier: License :: OSI Approved :: MIT License
Classifier: Operating System :: OS Independent
Classifier: Programming Language :: Python :: 3
Classifier: Programming Language :: Python :: 3.7
Classifier: Programming Language :: Python :: 3.8
Classifier: Programming Language :: Python :: 3.9
Requires-Python: >=3.7
License-File: LICENSE
Requires-Dist: pydantic >=2.0.0
Requires-Dist: pydantic-settings >=2.0.0
Requires-Dist: openai >=1.0.0
Requires-Dist: anthropic >=0.3.0
Requires-Dist: aiohttp >=3.7.4
Requires-Dist: beautifulsoup4 >=4.9.3
Requires-Dist: trafilatura >=1.4.0
Requires-Dist: opentelemetry-api >=1.12.0
Requires-Dist: opentelemetry-sdk >=1.12.0
Requires-Dist: asyncio >=3.4.3
Provides-Extra: dev
Requires-Dist: pytest >=6.2.5 ; extra == 'dev'
Requires-Dist: pytest-asyncio >=0.15.1 ; extra == 'dev'
Requires-Dist: black >=21.9b0 ; extra == 'dev'
Requires-Dist: isort >=5.9.3 ; extra == 'dev'
